{"creq-id":"82","major":"Applied Climate Science","concentrations":{"Bachelor of Science":{"semesters":{"1":{"courses":[{"creq-id":"2424","course":"AGRI 103","hours":"3","title":"Introduction to Agricultural and Natural Resource Systems"},{"creq-id":"3536","course":"MATH 106","hours":"5","title":"Calculus I"},{"creq-id":null,"course":"ENGL 150, 151, 254; JGEN 120, 200","hours":"3","title":null},{"creq-id":null,"course":"BIOS 101\/101L or LIFE 120\/120L or LIFE 121\/121L","hours":"4","title":null}]},"2":{"courses":[{"creq-id":"6641","course":"AGRO 153","hours":"4","title":"Soil Resources"},{"creq-id":null,"course":"ALEC 102; COMM 109, 209, 210, 283, 286; JGEN 300","hours":"3","title":null},{"creq-id":"3538","course":"MATH 107","hours":"4","title":"Calculus II"},{"creq-id":null,"course":"AECN 141 or ECON 211 or ECON 212","hours":"3","title":null}]},"3":{"courses":[{"creq-id":"4295","course":"CHEM 109","hours":"4","title":"General Chemistry I"},{"creq-id":"4212","course":"NRES 220","hours":"3","title":"Principles of Ecology"},{"creq-id":"4214","course":"NRES 222","hours":"1","title":"Ecology Laboratory"},{"creq-id":"2935","course":"WATS 281","hours":"3","title":"Introduction to Water Science"},{"creq-id":"3396","course":"METR 100","hours":"4","title":"Weather and Climate"}]},"4":{"courses":[{"creq-id":"3863","course":"PHYS 211","hours":"4","title":"General Physics I"},{"creq-id":null,"course":"ACE 5, 7, 8, or 9","hours":"3","title":null},{"creq-id":null,"course":"CSCE 155N or CSCE 155T","hours":"3","title":null},{"creq-id":"2824","course":"STAT 218","hours":"3","title":"Introduction to Statistics"},{"creq-id":"3398","course":"NRES 370","hours":"3","title":"Basic and Applied Climatology"}]},"5":{"courses":[{"creq-id":"3397","course":"METR 205","hours":"4","title":"Introduction to Atmospheric Science"},{"creq-id":"2888","course":"NRES 408\/808","hours":"3","title":"Microclimate: The Biological Environment"},{"creq-id":null,"course":"Specialization Requirement\/Elective","hours":"3","title":null},{"creq-id":null,"course":"Specialization Requirement\/Elective","hours":"3","title":null},{"creq-id":null,"course":"ACE 5, 7, 8, or 9","hours":"3","title":null}]},"6":{"courses":[{"creq-id":"3404","course":"NRES 478\/878","hours":"3","title":"Regional Climatology"},{"creq-id":"2909","course":"NRES 469\/869","hours":"3","title":"Bio-Atmospheric Instrumentation"},{"creq-id":null,"course":"NRES 312 or NRES 412","hours":"3","title":null},{"creq-id":null,"course":"ACE 5, 7, 8, or 9","hours":"3","title":null},{"creq-id":null,"course":"Specialization Requirement\/Elective","hours":"3","title":null}]},"7":{"courses":[{"creq-id":"6949","course":"METR 470\/870","hours":"3","title":"The Climate System: Analysis and Prediction"},{"creq-id":"7022","course":"METR 454\/854","hours":"3","title":"Statistical Analysis of Atmospheric Data"},{"creq-id":null,"course":"Specialization Requirement\/Elective","hours":"3","title":null},{"creq-id":null,"course":"Specialization Requirement\/Elective","hours":"3","title":null},{"creq-id":null,"course":"ACE 5, 7, 8, or 9","hours":"3","title":null}]},"8":{"courses":[{"creq-id":"2899","course":"NRES 452\/852","hours":"3","title":"Climate and Society"},{"creq-id":null,"course":"METR 483, 479, 487, or 475","hours":"3","title":null},{"creq-id":null,"course":"Specialization Requirement\/Elective","hours":"4","title":null},{"creq-id":null,"course":"Specialization Requirement\/Elective","hours":"4","title":null}]}},"notes":""}}}