{"creq-id":"121","major":"Mild\/Moderate Disabilities Education (7-12)","concentrations":{"Mild\/Moderate Disabilities Education (7-12)":{"1":"Individualize learning, and provide meaningful and challenging learning experiences for individuals with exceptionalities.","2":"Create safe, inclusive, and culturally responsive learning environments.","3":"Use multiple methods of assessment and data-sources in making educational decisions.","4":"Select, adapt, and use a repertoire of evidence-based instructional strategies to advance learning.","5":"Apply professional and ethical principles to inform practice.","6":"Collaborate with families, schools, and communities to address the needs of individuals with exceptionalities.","7":"","8":"","9":"","10":"","11":"","12":"","notes":""}}}